{
  "id": "1200",
  "title": {
    "display": "Carlos Carpet",
    "list": "Carlos Carpet"
  },
  "artists": [
    {
      "name": "Isaiah Zagar",
      "externallinks": [
        {
          "url": "https://www.phillymagicgardens.org/",
          "label": "phillymagicgardens.org"
        }
      ]
    }
  ],
  "years": [
    {
      "year": "2000"
    }
  ],
  "yearmodifier": "repaired 2011",
  "location": {
    "latitude": "39.941085",
    "longitude": "-75.151425",
    "description": "North side of Bainbridge West of 5th"
  },
  "architecture": {
    "description": "Walls"
  },
  "content": [
    {
      "description": "abstract forms",
      "separator": ","
    },
    {
      "description": "dogs",
      "separator": ","
    },
    {
      "description": "parts of people",
      "separator": ","
    },
    {
      "description": "cursive words",
      "separator": ","
    },
    {
      "description": "plants",
      "separator": ","
    },
    {
      "description": "bottles"
    }
  ],
  "externallinks": [
    {
      "url": "https://imgur.com/WDVBfPR",
      "label": "first official picture of this piece at imgur.com"
    },
    {
      "url": "https://imgur.com/pucXhWP",
      "label": "second official picture of this piece at imgur.com"
    }
  ],
  "pictures": [
    {
      "small": {
        "url": "https://www.philart.net/images/small/carloscarpet.gif",
        "mimetype": "image/gif"
      },
      "large": {
        "url": "https://www.philart.net/images/large/carloscarpet.jpg",
        "mimetype": "image/jpeg"
      }
    },
    {
      "small": {
        "url": "https://www.philart.net/images/small/carloscarpet2.gif",
        "mimetype": "image/gif"
      },
      "large": {
        "url": "https://www.philart.net/images/large/carloscarpet2.jpg",
        "mimetype": "image/jpeg"
      }
    }
  ],
  "tours": [
    {
      "name": "Lombard-South"
    }
  ]
}