{
  "id": "22",
  "title": {
    "display": "Ben Franklin",
    "list": "Ben Franklin (Lundeen)"
  },
  "artists": [
    {
      "name": "George Lundeen",
      "externallinks": [
        {
          "url": "https://lundeensculpture.com/bio-george/",
          "label": "lundeensculpture.com's George Lundeen page"
        }
      ]
    }
  ],
  "years": [
    {
      "year": "1987"
    }
  ],
  "location": {
    "latitude": "39.952150",
    "longitude": "-75.196975",
    "description": "East side of 37th Street, just South of Locust Walk"
  },
  "comments": "Title is from the artist's web page",
  "content": [
    {
      "description": "seated person",
      "separator": ","
    },
    {
      "description": "bench",
      "separator": ","
    },
    {
      "description": "eyeglasses",
      "separator": ","
    },
    {
      "description": "cane",
      "separator": ","
    },
    {
      "description": "newspaper",
      "separator": ","
    },
    {
      "description": "pigeon"
    }
  ],
  "peopleprefix": "Statue of",
  "people": [
    {
      "name": "Benjamin Franklin",
      "externallinks": [
        {
          "url": "https://en.wikipedia.org/wiki/Benjamin_Franklin",
          "label": "wikipedia.org's Benjamin Franklin page"
        }
      ]
    }
  ],
  "externallinks": [
    {
      "url": "https://www.associationforpublicart.org/artwork/benjamin-franklin-on-a-bench/",
      "label": "associationforpublicart.org's page for this piece"
    },
    {
      "url": "https://facilities.upenn.edu/maps/art/ben-franklin",
      "label": "upenn.edu's page for this piece"
    }
  ],
  "pictures": [
    {
      "small": {
        "url": "https://www.philart.net/images/small/benfben.gif",
        "mimetype": "image/gif"
      },
      "large": {
        "url": "https://www.philart.net/images/large/benfben.jpg",
        "mimetype": "image/jpeg"
      }
    },
    {
      "small": {
        "url": "https://www.philart.net/images/small/benfben2.gif",
        "mimetype": "image/gif"
      },
      "large": {
        "url": "https://www.philart.net/images/large/benfben2.jpg",
        "mimetype": "image/jpeg"
      }
    },
    {
      "small": {
        "url": "https://www.philart.net/images/small/benfben3.gif",
        "mimetype": "image/gif"
      },
      "large": {
        "url": "https://www.philart.net/images/large/benfben3.jpg",
        "mimetype": "image/jpeg"
      }
    },
    {
      "small": {
        "url": "https://www.philart.net/images/small/benfben4.gif",
        "mimetype": "image/gif"
      },
      "large": {
        "url": "https://www.philart.net/images/large/benfben4.jpg",
        "mimetype": "image/jpeg"
      }
    }
  ],
  "tours": [
    {
      "name": "Penn Campus"
    }
  ]
}