{
  "id": "645",
  "title": {
    "display": "Column and Capital",
    "list": "Column and Capital"
  },
  "years": [
    {
      "year": "1976"
    }
  ],
  "yearmodifier": "donated, obviously much older",
  "location": {
    "latitude": "39.951100",
    "longitude": "-75.191700",
    "description": "In a small park South of Smith Walk between 33rd and 34th"
  },
  "inscription": "<br />Ammen, Jordan  <br />(ancient Philadelphia)  <br />Roman Period  <br />Gift to City of Philadelphia  from the   Hashemite Kingdom of Jordan  on the occasion of the  American Bicentenial, 1976",
  "content": [
    {
      "description": "column and capital"
    }
  ],
  "externallinks": [
    {
      "url": "https://facilities.upenn.edu/maps/art/column-capital",
      "label": "upenn.edu's page for this piece"
    }
  ],
  "pictures": [
    {
      "small": {
        "url": "https://www.philart.net/images/small/ammen.gif",
        "mimetype": "image/gif"
      },
      "large": {
        "url": "https://www.philart.net/images/large/ammen.jpg",
        "mimetype": "image/jpeg"
      }
    }
  ],
  "tours": [
    {
      "name": "Penn Campus"
    }
  ]
}