{
  "id": "697",
  "title": {
    "display": "Balance",
    "list": "Balance"
  },
  "artists": [
    {
      "name": "Jill Sablosky",
      "externallinks": [
        {
          "url": "https://www.jillsablosky.com/",
          "label": "jillsablosky.com"
        }
      ]
    }
  ],
  "years": [
    {
      "year": "2009"
    }
  ],
  "location": {
    "latitude": "39.953550",
    "longitude": "-75.151600",
    "description": "Northwest corner, 7th and Appletree"
  },
  "inscription": "<br />E Pluribus Unum  <br />Out of Many One",
  "content": [
    {
      "description": "abstract"
    },
    {
      "description": "furniture forms",
      "separator": ","
    },
    {
      "description": "steles",
      "separator": ","
    },
    {
      "description": "ideas"
    }
  ],
  "externallinks": [
    {
      "url": "https://www.associationforpublicart.org/artwork/balance/",
      "label": "associationforpublicart.org's page for this piece"
    },
    {
      "url": "https://www.jillsablosky.com/new-gallery-5",
      "label": "artist's page for this piece"
    }
  ],
  "pictures": [
    {
      "small": {
        "url": "https://www.philart.net/images/small/7balance.gif",
        "mimetype": "image/gif"
      },
      "large": {
        "url": "https://www.philart.net/images/large/7balance.jpg",
        "mimetype": "image/jpeg"
      }
    },
    {
      "small": {
        "url": "https://www.philart.net/images/small/7balance2.gif",
        "mimetype": "image/gif"
      },
      "large": {
        "url": "https://www.philart.net/images/large/7balance2.jpg",
        "mimetype": "image/jpeg"
      }
    }
  ],
  "tours": [
    {
      "name": "Independence Mall"
    }
  ]
}