{
  "id": "747",
  "title": {
    "display": "Pennsylvania National Guard Monument",
    "list": "Pennsylvania National Guard Monument"
  },
  "years": [
    {
      "year": "1997"
    }
  ],
  "location": {
    "latitude": "39.941850",
    "longitude": "-75.141325",
    "description": "Penn's Landing between Dock and South"
  },
  "inscription": "<br />The rampant lion.  Crest of the PA National Guard.  <br />1747 1997  <br />  Near this site the <i>Associators</i>,  a group of citizen-soldiers organized by  Benjamin Franklin and predecessor to the  modern Pennsylvania National Guard,  established the first Pennsylvania  military installation to defend the colony  and the port of Philadelphia.<br />  The Pennsylvania National Guard dedicates this  monument to those patriots on our two hundredth  anniversary.",
  "content": [
    {
      "description": "lion",
      "separator": ","
    },
    {
      "description": "sword and shield",
      "separator": ","
    },
    {
      "description": "keystone"
    }
  ],
  "peopleprefix": "Monument to a group organized by",
  "people": [
    {
      "name": "Benjamin Franklin",
      "externallinks": [
        {
          "url": "https://en.wikipedia.org/wiki/Benjamin_Franklin",
          "label": "wikipedia.org's Benjamin Franklin page"
        }
      ]
    }
  ],
  "pictures": [
    {
      "small": {
        "url": "https://www.philart.net/images/small/panatguard.gif",
        "mimetype": "image/gif"
      },
      "large": {
        "url": "https://www.philart.net/images/large/panatguard.jpg",
        "mimetype": "image/jpeg"
      }
    },
    {
      "small": {
        "url": "https://www.philart.net/images/small/panatguard2.gif",
        "mimetype": "image/gif"
      },
      "large": {
        "url": "https://www.philart.net/images/large/panatguard2.jpg",
        "mimetype": "image/jpeg"
      }
    }
  ],
  "tours": [
    {
      "name": "Penn's Landing"
    }
  ]
}