{
  "id": "947",
  "title": {
    "display": "Bike Cloud",
    "list": "Bike Cloud (Logan Square)"
  },
  "artists": [
    {
      "name": "Ralph Tullie",
      "externallinks": [
        {
          "url": "https://www.linkedin.com/in/ralphjtullie/",
          "label": "Ralph Tullie's profile on linkedin.com"
        }
      ]
    }
  ],
  "years": [
    {
      "year": "2014"
    }
  ],
  "location": {
    "latitude": "39.957705",
    "longitude": "-75.169710",
    "description": "West side of Sister Cities Park, Northwest of 18th and Race"
  },
  "architecture": {
    "description": "Bike rack"
  },
  "content": [
    {
      "description": "abstract"
    },
    {
      "description": "cloud"
    }
  ],
  "landmark": {
    "name": "Logan Square",
    "prefix": "East side of",
    "externallinks": [
      {
        "url": "https://en.wikipedia.org/wiki/Logan_Circle_(Philadelphia)",
        "label": "wikipedia.org's Logan Circle page"
      }
    ]
  },
  "pictures": [
    {
      "small": {
        "url": "https://www.philart.net/images/small/bikecloud1.gif",
        "mimetype": "image/gif"
      },
      "large": {
        "url": "https://www.philart.net/images/large/bikecloud1.jpg",
        "mimetype": "image/jpeg"
      }
    },
    {
      "small": {
        "url": "https://www.philart.net/images/small/bikecloud2.gif",
        "mimetype": "image/gif"
      },
      "large": {
        "url": "https://www.philart.net/images/large/bikecloud2.jpg",
        "mimetype": "image/jpeg"
      }
    }
  ],
  "tours": [
    {
      "name": "Parkway and Pennsylvania"
    }
  ]
}