{
  "id": "976",
  "title": {
    "display": "Marino Monument",
    "list": "Marino Monument"
  },
  "artists": [
    {
      "name": "Harold Kimmelman",
      "externallinks": [
        {
          "url": "http://www.hksculpt.com/",
          "label": "hksculpt.com"
        }
      ]
    }
  ],
  "years": [
    {
      "year": "1977"
    }
  ],
  "location": {
    "latitude": "39.944320",
    "longitude": "-75.164010",
    "description": "Southeast of Juniper and Lombard"
  },
  "comments": "Visible through the fence on both sides",
  "inscription": "<br />Deputy Regional Administrator HUD Region 3  <br />THE IDEAL CIVIL SERVANT  <br />His dedication and talent helped build  <br />CASA ENRICO FERMI CORP.",
  "architecture": {
    "description": "Courtyard"
  },
  "content": [
    {
      "description": "standing person",
      "separator": ","
    },
    {
      "description": "abstract"
    },
    {
      "description": "architectural elements"
    }
  ],
  "landmark": {
    "name": "Casa Farnese Apartments",
    "prefix": "West side of the"
  },
  "peopleprefix": "Sculpture in memory of",
  "people": [
    {
      "name": "Vincent A. Marino, Esq.",
      "externallinks": [
        {
          "url": "https://www.findagrave.com/memorial/187057611/vincent-a_-marino",
          "label": "findagrave.com's Vincent A. Marino page"
        }
      ]
    }
  ],
  "externallinks": [
    {
      "url": "http://www.hksculpt.com/addedbackpages/newBackpages/Marino.htm",
      "label": "artist's page for this piece"
    }
  ],
  "pictures": [
    {
      "small": {
        "url": "https://www.philart.net/images/small/vamarino.gif",
        "mimetype": "image/gif"
      },
      "large": {
        "url": "https://www.philart.net/images/large/vamarino.jpg",
        "mimetype": "image/jpeg"
      }
    },
    {
      "small": {
        "url": "https://www.philart.net/images/small/vamarino2.gif",
        "mimetype": "image/gif"
      },
      "large": {
        "url": "https://www.philart.net/images/large/vamarino2.jpg",
        "mimetype": "image/jpeg"
      }
    },
    {
      "small": {
        "url": "https://www.philart.net/images/small/vamarino3.gif",
        "mimetype": "image/gif"
      },
      "large": {
        "url": "https://www.philart.net/images/large/vamarino3.jpg",
        "mimetype": "image/jpeg"
      }
    }
  ],
  "tours": [
    {
      "name": "Avenue of the Arts"
    }
  ]
}